emmivox/__init__.py
emmivox/bibtex.py
emmivox/constants.py
emmivox/icon.png
emmivox/protocols.conf
emmivox/protocols/__init__.py
emmivox/protocols/protocol_hello_world.py
emmivox/tests/__init__.py
emmivox/viewers/__init__.py
emmivox/wizards/__init__.py
emmivox/wizards/wizard_hello_world.py
scipion_em_emmivox-0.1.dist-info/LICENSE
scipion_em_emmivox-0.1.dist-info/METADATA
scipion_em_emmivox-0.1.dist-info/WHEEL
scipion_em_emmivox-0.1.dist-info/entry_points.txt
scipion_em_emmivox-0.1.dist-info/top_level.txt
scipion_em_emmivox-0.1.dist-info/RECORD
