Metadata-Version: 2.1
Name: scipion-em-emmivox
Version: 0.1
Summary: Scipion plugin emmivox
Author-email: "James M. Krieger" <jamesmkrieger@gmail.com>
License: GNU General Public License v3 (GPLv3)
Project-URL: Homepage, https://github.com/scipion-em/scipion-em-emmivox
Project-URL: Issues, https://github.com/scipion-em/scipion-em-emmivox/issues
Keywords: scipion,cryoem,imageprocessing,scipion-3.0,flexiblefitting,modelrefinement,dynamics,ensemble
Classifier: Development Status :: 3 - Alpha
Classifier: License :: OSI Approved :: GNU General Public License v3 (GPLv3)
Classifier: Programming Language :: Python :: 3
Requires-Python: >=3.8
License-File: LICENSE
Requires-Dist: scipion-pyworkflow
Requires-Dist: scipion-em
